fun_functions_lib-0.2.0.dist-info/licenses/LICENSE
functions/__init__.py
functions/core.py
fun_functions_lib-0.2.0.dist-info/METADATA
fun_functions_lib-0.2.0.dist-info/WHEEL
fun_functions_lib-0.2.0.dist-info/top_level.txt
fun_functions_lib-0.2.0.dist-info/RECORD
